{"cameraMode":{"drawMode":0,"name":"Shaded","section":"Shading Mode"},"sceneLighting":true,"audioPlay":false,"sceneViewState":{"m_AlwaysRefresh":false,"showFog":true,"showSkybox":true,"showFlares":true,"showImageEffects":true,"showParticleSystems":true,"showVisualEffectGraphs":true,"m_FxEnabled":true},"in2DMode":false,"pivot":{"x":0.25658154487609866,"y":8.37794303894043,"z":5.153163909912109},"rotation":{"x":-0.0695638656616211,"y":-0.9292714595794678,"z":0.2312512844800949,"w":-0.27953824400901797},"size":18.371641159057618,"orthographic":true}